stabilizer_timelime/src/__init__.py
stabilizer_timelime/src/dataslurper/__init__.py
stabilizer_timelime/src/dataslurper/prudenceChecker.py
stabilizer_timelime/src/dataslurper/slurpdata.py
stabilizer_timelime/src/stabilizer/__init__.py
stabilizer_timelime/src/stabilizer/config.py
stabilizer_timelime/src/stabilizer/src/.DS_Store
stabilizer_timelime/src/stabilizer/src/CFS.py
stabilizer_timelime/src/stabilizer/src/CFS_regression.py
stabilizer_timelime/src/stabilizer/src/DE.py
stabilizer_timelime/src/stabilizer/src/Find_bellwethers.py
stabilizer_timelime/src/stabilizer/src/Performance_Calculator.py
stabilizer_timelime/src/stabilizer/src/Stats_files.py
stabilizer_timelime/src/stabilizer/src/__init__.py
stabilizer_timelime/src/stabilizer/src/attribute_selector.py
stabilizer_timelime/src/stabilizer/src/birch.py
stabilizer_timelime/src/stabilizer/src/birch_bellwether_p_CFS.py
stabilizer_timelime/src/stabilizer/src/collect_bellwethers.py
stabilizer_timelime/src/stabilizer/src/default_bellwether.py
stabilizer_timelime/src/stabilizer/src/generate_results.py
stabilizer_timelime/src/stabilizer/src/init_datafiles.py
stabilizer_timelime/src/stabilizer/src/learners.py
stabilizer_timelime/src/stabilizer/src/optimizer.py
stabilizer_timelime/src/stabilizer/src/predictor_advance_v1.py
stabilizer_timelime/src/stabilizer/src/predictor_baseline.py
stabilizer_timelime/src/stabilizer/src/scott_knott.py
stabilizer_timelime/src/stabilizer/src/utils.py
stabilizer_timelime/src/timeLIME/__init__.py
stabilizer_timelime/src/timeLIME/src/__init__.py
stabilizer_timelime/src/timeLIME/src/othertools.py
stabilizer_timelime/src/timeLIME/src/planner.py
stabilizer_timelime/src/timeLIME/src/runexp.py
stabilizer_timelime/src/timeLIME/src/split_dataset.py
stabilizer_timelime-0.2.1.dist-info/LICENSE
stabilizer_timelime-0.2.1.dist-info/METADATA
stabilizer_timelime-0.2.1.dist-info/WHEEL
stabilizer_timelime-0.2.1.dist-info/RECORD
